{
  "type": "lootbags:loot",
  "name": "Animal Crossing Common Decorations Kit",
  "rarity": "UNCOMMON",
  "output": {
    "rolls": 1,
    "entries": [
      {
        "stack": "luphieclutteredmod:luphie_general_store_cabinet",
        "weight": 1
      },
      {
        "stack": "luphieclutteredmod:luphie_art_academy_box_of_paint",
        "weight": 1
      },
      {
        "stack": "luphieclutteredmod:luphie_mermaid_dresser",
        "weight": 1
      },
      {
        "stack": "luphieclutteredmod:luphie_briefcase",
        "weight": 1
      },
      {
        "stack": "luphieclutteredmod:luphie_lunar_observatory_basket_of_papers",
        "weight": 1
      },
      {
        "stack": "luphieclutteredmod:luphie_lunar_observatory_globe",
        "weight": 1
      },
      {
        "stack": "luphieclutteredmod:luphie_lunar_observatory_jars",
        "weight": 1
      },
      {
        "stack": "luphieclutteredmod:luphie_lunar_observatory_small_table",
        "weight": 1
      },
      {
        "stack": "luphieclutteredmod:luphie_lunar_observatory_table",
        "weight": 1
      },
      {
        "stack": "luphieclutteredmod:luphie_small_cauldron_set",
        "weight": 1
      },
      {
        "stack": "luphieclutteredmod:luphie_pastel_block_bookshelf",
        "weight": 1
      },
      {
        "stack": "luphieclutteredmod:luphie_lunar_observatory_books",
        "weight": 1
      },
      {
        "stack": "luphieclutteredmod:luphie_baking_set_a",
        "weight": 1
      },
      {
        "stack": "luphieclutteredmod:luphie_pastel_traditional_table",
        "weight": 1
      },
      {
        "stack": "luphieclutteredmod:luphie_coffee_grinder",
        "weight": 1
      },
      {
        "stack": "luphieclutteredmod:luphie_retro_cafe_shelf",
        "weight": 1
      },
      {
        "stack": "luphieclutteredmod:luphie_retro_cafe_shelf_stained_glass",
        "weight": 1
      },
      {
        "stack": "luphieclutteredmod:luphie_rovers_mug",
        "weight": 1
      },
      {
        "stack": "luphieclutteredmod:luphie_rovers_stool",
        "weight": 1
      },
      {
        "stack": "luphieclutteredmod:luphie_analog_kitchen_scale",
        "weight": 1
      },
      {
        "stack": "luphieclutteredmod:luphie_apple_chair",
        "weight": 1
      },
      {
        "stack": "luphieclutteredmod:luphie_button_stool",
        "weight": 1
      },
      {
        "stack": "luphieclutteredmod:luphie_green_gumball_machine",
        "weight": 1
      },
      {
        "stack": "luphieclutteredmod:luphie_purple_gumball_machine",
        "weight": 1
      },
      {
        "stack": "luphieclutteredmod:luphie_mermaid_pearl",
        "weight": 1
      },
      {
        "stack": "luphieclutteredmod:luphie_potion_shelf",
        "weight": 1
      },
      {
        "stack": "luphieclutteredmod:luphie_sewing_table_clutter",
        "weight": 1
      }
    ]
  }
}