{
  "type": "lootbags:loot",
  "name": "Cluttered Mod Misc Common Decorations Kit",
  "rarity": "UNCOMMON",
  "output": {
    "rolls": 1,
    "entries": [
      {
        "stack": "luphieclutteredmod:luphie_antique_sewing_machine",
        "weight": 1
      },
      {
        "stack": "luphieclutteredmod:luphie_empty_bulletin_board",
        "weight": 1
      },
      {
        "stack": "luphieclutteredmod:luphie_cauldron_poster",
        "weight": 1
      },
      {
        "stack": "luphieclutteredmod:luphie_cluttered_seltzer_cans",
        "weight": 1
      },
      {
        "stack": "luphieclutteredmod:luphie_envelope_stack",
        "weight": 1
      },
      {
        "stack": "luphieclutteredmod:luphie_hanging_dish_towel",
        "weight": 1
      },
      {
        "stack": "luphieclutteredmod:luphie_key",
        "weight": 1
      },
      {
        "stack": "luphieclutteredmod:luphie_office_box",
        "weight": 1
      },
      {
        "stack": "luphieclutteredmod:luphie_office_supplies_clutter",
        "weight": 1
      },
      {
        "stack": "luphieclutteredmod:luphie_salt_and_pepper_shakers",
        "weight": 1
      },
      {
        "stack": "luphieclutteredmod:luphie_sewing_clutter",
        "weight": 1
      },
      {
        "stack": "luphieclutteredmod:luphie_vial_stand",
        "weight": 1
      },
      {
        "stack": "luphieclutteredmod:luphie_cluttered_cat_mugs",
        "weight": 1
      },
      {
        "stack": "luphieclutteredmod:luphie_tea_kettle",
        "weight": 1
      },
      {
        "stack": "luphieclutteredmod:luphie_heart_cake",
        "weight": 1
      },
      {
        "stack": "luphieclutteredmod:luphie_heart_armchair",
        "weight": 1
      },
      {
        "stack": "luphieclutteredmod:luphie_paint_water_jar",
        "weight": 1
      },
      {
        "stack": "luphieclutteredmod:luphie_polaroid_camera",
        "weight": 1
      },
      {
        "stack": "luphieclutteredmod:plant_ladder",
        "weight": 1
      }
    ]
  }
}