{
	"minecraft:trapezoid": "net.minecraft.world.level.levelgen.heightproviders.HeightProviderType$$Lambda$2657/0x000001550aa966a8",
	"minecraft:weighted_list": "net.minecraft.world.level.levelgen.heightproviders.HeightProviderType$$Lambda$2657/0x000001550aa966a8",
	"minecraft:very_biased_to_bottom": "net.minecraft.world.level.levelgen.heightproviders.HeightProviderType$$Lambda$2657/0x000001550aa966a8",
	"minecraft:biased_to_bottom": "net.minecraft.world.level.levelgen.heightproviders.HeightProviderType$$Lambda$2657/0x000001550aa966a8",
	"minecraft:uniform": "net.minecraft.world.level.levelgen.heightproviders.HeightProviderType$$Lambda$2657/0x000001550aa966a8",
	"minecraft:constant": "net.minecraft.world.level.levelgen.heightproviders.HeightProviderType$$Lambda$2657/0x000001550aa966a8"
}