{
	"minecraft:biased_to_bottom": "net.minecraft.world.level.levelgen.heightproviders.HeightProviderType$$Lambda$2678/0x0000023225b16f88",
	"minecraft:constant": "net.minecraft.world.level.levelgen.heightproviders.HeightProviderType$$Lambda$2678/0x0000023225b16f88",
	"minecraft:weighted_list": "net.minecraft.world.level.levelgen.heightproviders.HeightProviderType$$Lambda$2678/0x0000023225b16f88",
	"minecraft:trapezoid": "net.minecraft.world.level.levelgen.heightproviders.HeightProviderType$$Lambda$2678/0x0000023225b16f88",
	"minecraft:very_biased_to_bottom": "net.minecraft.world.level.levelgen.heightproviders.HeightProviderType$$Lambda$2678/0x0000023225b16f88",
	"minecraft:uniform": "net.minecraft.world.level.levelgen.heightproviders.HeightProviderType$$Lambda$2678/0x0000023225b16f88",
	"underground_villages:constant": "com.mrbysco.undergroundvillages.registry.ModHeightProvider$$Lambda$21297/0x0000023227a13a48"
}