{
  "bookshelf:load_conditions": [
    {
      "type": "bookshelf:item_exists",
      "values": [
        "minecraft:sunflower"
      ]
    }
  ],
  "type": "botanypots:crop",
  "seed": {
    "item": "minecraft:sunflower"
  },
  "categories": [
    "dirt",
    "farmland"
  ],
  "growthTicks": 2000,
  "display": {
    "type": "botanypots:aging",
    "block": "minecraft:sunflower"
  },
  "drops": [
    {
      "chance": 1.0,
      "output": {
        "item": "minecraft:sunflower"
      }
    },
    {
      "chance": 0.01,
      "output": {
        "item": "minecraft:sunflower"
      }
    }
  ]
}